pysensorsdata/__init__.py
pysensorsdata/_version.py
pysensorsdata/common.py
pysensorsdata/exc.py
pysensorsdata/hive.py
pysensorsdata/sasl_compat.py
pysensorsdata/sqlalchemy.py
pysensorsdata/_thrift_gen/__init__.py
pysensorsdata/_thrift_gen/TCLIService/TCLIService.py
pysensorsdata/_thrift_gen/TCLIService/__init__.py
pysensorsdata/_thrift_gen/TCLIService/constants.py
pysensorsdata/_thrift_gen/TCLIService/ttypes.py
pysensorsdata/tests/__init__.py
pysensorsdata/tests/dbapi_test_case.py
pysensorsdata/tests/sqlalchemy_test_case.py
pysensorsdata/tests/test_common.py
pysensorsdata/tests/test_hive.py
pysensorsdata/tests/test_sasl_compat.py
pysensorsdata/tests/test_sqlalchemy_hive.py
pysensorsdata-0.1.0.dev0.dist-info/METADATA
pysensorsdata-0.1.0.dev0.dist-info/WHEEL
pysensorsdata-0.1.0.dev0.dist-info/entry_points.txt
pysensorsdata-0.1.0.dev0.dist-info/top_level.txt
pysensorsdata-0.1.0.dev0.dist-info/RECORD
